suno/__init__.py
suno/__main__.py
suno/suno.py
suno_songs-0.6.0.dist-info/LICENSE
suno_songs-0.6.0.dist-info/METADATA
suno_songs-0.6.0.dist-info/WHEEL
suno_songs-0.6.0.dist-info/entry_points.txt
suno_songs-0.6.0.dist-info/top_level.txt
suno_songs-0.6.0.dist-info/RECORD
