Metadata-Version: 2.1
Name: suno_songs
Version: 0.6.0
Summary: High quality songs generation by suno.ai. Reverse engineered API.
Home-page: https://github.com/yihong0618/SunoSongsCreator
Author: yihong0618
Author-email: zouzou0208@gmail.com
Project-URL: Bug Report, https://github.com/yihong0618/SunoSongsCreator/issues/new
Classifier: Intended Audience :: Developers
Classifier: Topic :: Software Development :: Libraries :: Python Modules
Classifier: Programming Language :: Python :: 3.8
Classifier: Programming Language :: Python :: 3.9
Classifier: Programming Language :: Python :: 3.10
Classifier: Programming Language :: Python :: 3.11
Classifier: Programming Language :: Python :: 3.12
License-File: LICENSE
Requires-Dist: curl-cffi
Requires-Dist: requests
Requires-Dist: fake-useragent
Requires-Dist: rich
Requires-Dist: python-dotenv
